<?xml version="1.0" encoding="utf-8"?>
<publishData>
  <publishProfile publishUrl="\\3.41.199.73\PMMWS" deleteExistingFiles="False" ftpAnonymousLogin="False" ftpPassiveMode="True" msdeploySite="PMMWS" msdeploySiteID="" msdeployRemoteSitePhysicalPath="" msdeployAllowUntrustedCertificate="False" msdeploySkipExtraFilesOnServer="True" msdeployMarkAsApp="True" profileName="配置文件1" publishMethod="FileSystem" replaceMatchingFiles="True" userName="asze-public" savePWD="False" userPWD="" SelectedForPublish="True">
    <file relUrl="bin/NHibernate.dll" publishTime="11/21/2005 19:32:58" />
    <file relUrl="Default.aspx" publishTime="01/18/2012 14:53:48" />
    <file relUrl="bin/DevExpress.PivotGrid.v11.1.Core.dll" publishTime="11/29/2011 10:58:51" />
    <file relUrl="bin/PMMWS.pdb" publishTime="02/07/2012 15:41:02" />
    <file relUrl="WorkOrderAdmin.aspx" publishTime="02/07/2012 09:47:00" />
    <file relUrl="bin/DevExpress.Web.ASPxGridView.v11.1.dll" publishTime="11/29/2011 10:58:25" />
    <file relUrl="bin/PMMWS.dll" publishTime="02/07/2012 15:41:02" />
    <file relUrl="bin/Castle.ActiveRecord.xml" publishTime="01/01/2006 15:18:18" />
    <file relUrl="Web.config" publishTime="01/12/2012 15:33:26" />
    <file relUrl="bin/DevExpress.Web.v11.1.dll" publishTime="11/29/2011 10:58:26" />
    <file relUrl="bin/DevExpress.Utils.v11.1.dll" publishTime="11/29/2011 10:58:44" />
    <file relUrl="bin/Castle.Model.xml" publishTime="01/01/2006 15:17:24" />
    <file relUrl="bin/DevExpress.Web.ASPxEditors.v11.1.xml" publishTime="11/29/2011 10:58:24" />
    <file relUrl="StatuesColor/write.png" publishTime="11/25/2011 14:50:12" />
    <file relUrl="bin/DevExpress.XtraPrinting.v11.1.xml" publishTime="11/29/2011 10:58:51" />
    <file relUrl="bin/antlr.runtime.dll" publishTime="11/21/2005 19:42:18" />
    <file relUrl="MaintenanceWebInfo.aspx" publishTime="01/12/2012 17:09:56" />
    <file relUrl="ReportView.aspx" publishTime="12/02/2011 16:10:38" />
    <file relUrl="bin/DevExpress.Data.v11.1.dll" publishTime="11/29/2011 10:58:30" />
    <file relUrl="App_Data/MechineName.xml" publishTime="11/05/2011 00:12:46" />
    <file relUrl="bin/log4net.dll" publishTime="11/21/2005 19:34:44" />
    <file relUrl="OpMainPage.aspx" publishTime="01/12/2012 19:28:57" />
    <file relUrl="bin/DevExpress.Web.v11.1.xml" publishTime="11/29/2011 10:58:25" />
    <file relUrl="TitleControl.ascx" publishTime="02/06/2012 10:24:48" />
    <file relUrl="bin/DevExpress.RichEdit.v11.1.Core.dll" publishTime="11/29/2011 10:58:53" />
    <file relUrl="bin/Castle.DynamicProxy.xml" publishTime="01/01/2006 15:17:10" />
    <file relUrl="bin/DevExpress.Web.ASPxEditors.v11.1.dll" publishTime="11/29/2011 10:58:25" />
    <file relUrl="bin/Iesi.Collections.dll" publishTime="11/21/2005 19:32:58" />
    <file relUrl="bin/DevExpress.Web.ASPxGridView.v11.1.Export.dll" publishTime="11/29/2011 10:58:25" />
    <file relUrl="bin/DevExpress.XtraRichEdit.v11.1.dll" publishTime="11/29/2011 10:58:53" />
    <file relUrl="bin/DevExpress.XtraReports.v11.1.dll" publishTime="11/29/2011 10:58:52" />
    <file relUrl="bin/Nullables.dll" publishTime="11/21/2005 19:32:58" />
    <file relUrl="Maintenance.aspx" publishTime="01/12/2012 18:45:43" />
    <file relUrl="EquipmentsInfo.aspx" publishTime="02/06/2012 10:10:18" />
    <file relUrl="bin/Castle.Model.dll" publishTime="01/01/2006 15:17:24" />
    <file relUrl="bin/DevExpress.XtraPivotGrid.v11.1.dll" publishTime="11/29/2011 10:58:51" />
    <file relUrl="bin/DevExpress.XtraReports.v11.1.Web.xml" publishTime="11/29/2011 10:58:51" />
    <file relUrl="bin/DevExpress.Web.ASPxGridView.v11.1.Export.xml" publishTime="11/29/2011 10:58:25" />
    <file relUrl="StatuesColor/Yellow.png" publishTime="11/25/2011 14:57:46" />
    <file relUrl="bin/DevExpress.Data.v11.1.xml" publishTime="11/29/2011 10:58:30" />
    <file relUrl="bin/Castle.ActiveRecord.dll" publishTime="01/01/2006 15:18:18" />
    <file relUrl="ld.aspx" publishTime="11/29/2011 12:19:40" />
    <file relUrl="bin/DevExpress.XtraCharts.v11.1.xml" publishTime="11/29/2011 10:58:49" />
    <file relUrl="SPInfo.aspx" publishTime="01/18/2012 16:48:39" />
    <file relUrl="bin/DevExpress.XtraEditors.v11.1.dll" publishTime="11/29/2011 10:58:50" />
    <file relUrl="bin/DevExpress.XtraRichEdit.v11.1.xml" publishTime="11/29/2011 10:58:53" />
    <file relUrl="MaintenanceWebInfoC.aspx" publishTime="12/07/2011 14:34:44" />
    <file relUrl="bin/DevExpress.Utils.v11.1.xml" publishTime="11/29/2011 10:58:44" />
    <file relUrl="bin/DevExpress.XtraCharts.v11.1.dll" publishTime="11/29/2011 10:58:49" />
    <file relUrl="bin/Castle.DynamicProxy.dll" publishTime="01/01/2006 15:17:10" />
    <file relUrl="StatuesColor/Green.png" publishTime="11/25/2011 15:08:52" />
    <file relUrl="bin/DevExpress.XtraCharts.v11.1.Web.xml" publishTime="11/29/2011 10:58:48" />
    <file relUrl="bin/DevExpress.XtraPivotGrid.v11.1.xml" publishTime="11/29/2011 10:58:51" />
    <file relUrl="RepairPageForm.aspx" publishTime="01/12/2012 19:29:41" />
    <file relUrl="mono_aviation.gif" publishTime="11/20/2011 10:14:04" />
    <file relUrl="bin/DevExpress.XtraReports.v11.1.xml" publishTime="11/29/2011 10:58:51" />
    <file relUrl="ChartingControl.aspx" publishTime="02/06/2012 10:44:27" />
    <file relUrl="bin/DevExpress.Printing.v11.1.Core.dll" publishTime="11/29/2011 10:58:37" />
    <file relUrl="bin/DevExpress.PivotGrid.v11.1.Core.xml" publishTime="11/29/2011 10:58:51" />
    <file relUrl="bin/DevExpress.XtraEditors.v11.1.xml" publishTime="11/29/2011 10:58:49" />
    <file relUrl="ge_logo.gif" publishTime="11/05/2011 11:01:52" />
    <file relUrl="bin/DevExpress.RichEdit.v11.1.Core.xml" publishTime="11/29/2011 10:58:53" />
    <file relUrl="WorkerInfo.aspx" publishTime="01/09/2012 16:52:44" />
    <file relUrl="bin/DevExpress.Charts.v11.1.Core.dll" publishTime="11/29/2011 10:58:49" />
    <file relUrl="MaintenancePlanForm.aspx" publishTime="01/18/2012 13:19:08" />
    <file relUrl="MaintenanceHistor.aspx" publishTime="01/17/2012 17:32:28" />
    <file relUrl="bin/DevExpress.XtraReports.v11.1.Web.dll" publishTime="11/29/2011 10:58:51" />
    <file relUrl="bin/DevExpress.Web.ASPxGridView.v11.1.xml" publishTime="11/29/2011 10:58:25" />
    <file relUrl="bin/DevExpress.XtraPrinting.v11.1.dll" publishTime="11/29/2011 10:58:51" />
    <file relUrl="MaintenanceWebInfoB.aspx" publishTime="12/07/2011 14:34:44" />
    <file relUrl="MaintenanceWebInfoD.aspx" publishTime="12/07/2011 14:34:44" />
    <file relUrl="bin/DevExpress.XtraCharts.v11.1.Web.dll" publishTime="11/29/2011 10:58:48" />
  </publishProfile>
</publishData>